composite_ufjc_scission_ufl_fenics/__init__.py
composite_ufjc_scission_ufl_fenics/characterizer.py
composite_ufjc_scission_ufl_fenics/composite_ufjc.py
composite_ufjc_scission_ufl_fenics/core.py
composite_ufjc_scission_ufl_fenics/default_parameters.py
composite_ufjc_scission_ufl_fenics/rate_dependence_scission.py
composite_ufjc_scission_ufl_fenics/scission_model.py
composite_ufjc_scission_ufl_fenics/utility.py
composite_ufjc_scission_ufl_fenics-1.4.0.dist-info/LICENSE
composite_ufjc_scission_ufl_fenics-1.4.0.dist-info/METADATA
composite_ufjc_scission_ufl_fenics-1.4.0.dist-info/WHEEL
composite_ufjc_scission_ufl_fenics-1.4.0.dist-info/top_level.txt
composite_ufjc_scission_ufl_fenics-1.4.0.dist-info/RECORD
